[
  {
    "_id": "25c3a297bd1da860675b5dff",
    "shop_id": "00001001",
    "shop_name": "CIRCLE K",
    "country_id": "VN",
    "province_id": "00",
    "district_id": "001",
    "ward_code": "00001",
    "house_number": "",
    "street": "Phố Hàng Than",
    "latitude": 21.04234,
    "longitude": 105.84714,
    "shop_type": "convenience"
  },
  {
    "_id": "5d6ea352b925d8227f5036e0",
    "shop_id": "00001002",
    "shop_name": "CIRCLE K",
    "country_id": "VN",
    "province_id": "00",
    "district_id": "001",
    "ward_code": "00001",
    "house_number": "85",
    "street": "Phố Hàng Mã",
    "latitude": 21.03656,
    "longitude": 105.84694,
    "shop_type": "convenience"
  },
  {
    "_id": "fac4ea703b31b7fa69470ae8",
    "shop_id": "00001003",
    "shop_name": "CIRCLE K",
    "country_id": "VN",
    "province_id": "00",
    "district_id": "001",
    "ward_code": "00001",
    "house_number": "38",
    "street": "Phố Đào Duy Từ",
    "latitude": 21.03599,
    "longitude": 105.85281,
    "shop_type": "convenience"
  },
  {
    "_id": "0a92d4c1f09e806c59991d00",
    "shop_id": "00004001",
    "shop_name": "CIRCLE K",
    "country_id": "VN",
    "province_id": "00",
    "district_id": "001",
    "ward_code": "00004",
    "house_number": "",
    "street": "Phố Hàng Than",
    "latitude": 21.04234,
    "longitude": 105.84714,
    "shop_type": "convenience"
  },
  {
    "_id": "36c010cd072203497b80ac10",
    "shop_id": "00004002",
    "shop_name": "CIRCLE K",
    "country_id": "VN",
    "province_id": "00",
    "district_id": "001",
    "ward_code": "00004",
    "house_number": "85",
    "street": "Phố Hàng Mã",
    "latitude": 21.03656,
    "longitude": 105.84694,
    "shop_type": "convenience"
  },
  {
    "_id": "2be7aa0392b70f6d2fc15f2b",
    "shop_id": "00004003",
    "shop_name": "CIRCLE K",
    "country_id": "VN",
    "province_id": "00",
    "district_id": "001",
    "ward_code": "00004",
    "house_number": "38",
    "street": "Phố Đào Duy Từ",
    "latitude": 21.03599,
    "longitude": 105.85281,
    "shop_type": "convenience"
  },
  {
    "_id": "ac37e9ed08d0c78f8298605f",
    "shop_id": "00006001",
    "shop_name": "CIRCLE K",
    "country_id": "VN",
    "province_id": "00",
    "district_id": "001",
    "ward_code": "00006",
    "house_number": "",
    "street": "Phố Hàng Than",
    "latitude": 21.04234,
    "longitude": 105.84714,
    "shop_type": "convenience"
  },
  {
    "_id": "604d4901cabf6a4b194265a3",
    "shop_id": "00006002",
    "shop_name": "CIRCLE K",
    "country_id": "VN",
    "province_id": "00",
    "district_id": "001",
    "ward_code": "00006",
    "house_number": "85",
    "street": "Phố Hàng Mã",
    "latitude": 21.03656,
    "longitude": 105.84694,
    "shop_type": "convenience"
  },
  {
    "_id": "b66edf9b7019cb9285991f22",
    "shop_id": "00006003",
    "shop_name": "CIRCLE K",
    "country_id": "VN",
    "province_id": "00",
    "district_id": "001",
    "ward_code": "00006",
    "house_number": "79",
    "street": "Phố Hà Trung",
    "latitude": 21.03001,
    "longitude": 105.84486,
    "shop_type": "convenience"
  },
  {
    "_id": "60a8195fbc5b233e1a1c5a63",
    "shop_id": "00007001",
    "shop_name": "CIRCLE K",
    "country_id": "VN",
    "province_id": "00",
    "district_id": "001",
    "ward_code": "00007",
    "house_number": "79",
    "street": "Phố Hà Trung",
    "latitude": 21.03001,
    "longitude": 105.84486,
    "shop_type": "convenience"
  },
  {
    "_id": "a60ce73d84c2e23f47efa4fa",
    "shop_id": "00007002",
    "shop_name": "CIRCLE K",
    "country_id": "VN",
    "province_id": "00",
    "district_id": "001",
    "ward_code": "00007",
    "house_number": "",
    "street": "Phố Hàng Bông",
    "latitude": 21.0293,
    "longitude": 105.84556,
    "shop_type": "convenience"
  },
  {
    "_id": "826ceae185e1be384d8e9336",
    "shop_id": "00007003",
    "shop_name": "CIRCLE K",
    "country_id": "VN",
    "province_id": "00",
    "district_id": "001",
    "ward_code": "00007",
    "house_number": "83",
    "street": "Phố Hàng Điếu",
    "latitude": 21.03206,
    "longitude": 105.84684,
    "shop_type": "convenience"
  },
  {
    "_id": "716a2e352631b9441f46e863",
    "shop_id": "00008001",
    "shop_name": "CIRCLE K",
    "country_id": "VN",
    "province_id": "00",
    "district_id": "001",
    "ward_code": "00008",
    "house_number": "79",
    "street": "Phố Hà Trung",
    "latitude": 21.03001,
    "longitude": 105.84486,
    "shop_type": "convenience"
  },
  {
    "_id": "540fc24b0056da3e4c445d5a",
    "shop_id": "00008002",
    "shop_name": "CIRCLE K",
    "country_id": "VN",
    "province_id": "00",
    "district_id": "001",
    "ward_code": "00008",
    "house_number": "",
    "street": "Phố Hàng Bông",
    "latitude": 21.0293,
    "longitude": 105.84556,
    "shop_type": "convenience"
  },
  {
    "_id": "509877284c78a1be32ed9c7d",
    "shop_id": "00008003",
    "shop_name": "CIRCLE K",
    "country_id": "VN",
    "province_id": "00",
    "district_id": "001",
    "ward_code": "00008",
    "house_number": "85",
    "street": "Phố Hàng Mã",
    "latitude": 21.03656,
    "longitude": 105.84694,
    "shop_type": "convenience"
  },
  {
    "_id": "cf0c24ab3f439770e26d163d",
    "shop_id": "00010001",
    "shop_name": "CIRCLE K",
    "country_id": "VN",
    "province_id": "00",
    "district_id": "001",
    "ward_code": "00010",
    "house_number": "",
    "street": "Phố Hàng Than",
    "latitude": 21.04234,
    "longitude": 105.84714,
    "shop_type": "convenience"
  },
  {
    "_id": "5dbba2df09deb55ca457278c",
    "shop_id": "00010002",
    "shop_name": "CIRCLE K",
    "country_id": "VN",
    "province_id": "00",
    "district_id": "001",
    "ward_code": "00010",
    "house_number": "85",
    "street": "Phố Hàng Mã",
    "latitude": 21.03656,
    "longitude": 105.84694,
    "shop_type": "convenience"
  },
  {
    "_id": "7b3bbe2b6a3430653db28484",
    "shop_id": "00010003",
    "shop_name": "CIRCLE K",
    "country_id": "VN",
    "province_id": "00",
    "district_id": "001",
    "ward_code": "00010",
    "house_number": "38",
    "street": "Phố Đào Duy Từ",
    "latitude": 21.03599,
    "longitude": 105.85281,
    "shop_type": "convenience"
  },
  {
    "_id": "f4b825837a840fde5e6af63d",
    "shop_id": "00013001",
    "shop_name": "CIRCLE K",
    "country_id": "VN",
    "province_id": "00",
    "district_id": "001",
    "ward_code": "00013",
    "house_number": "",
    "street": "Phố Hàng Than",
    "latitude": 21.04234,
    "longitude": 105.84714,
    "shop_type": "convenience"
  },
  {
    "_id": "89098b22a7b15045ee46f400",
    "shop_id": "00013002",
    "shop_name": "CIRCLE K",
    "country_id": "VN",
    "province_id": "00",
    "district_id": "001",
    "ward_code": "00013",
    "house_number": "85",
    "street": "Phố Hàng Mã",
    "latitude": 21.03656,
    "longitude": 105.84694,
    "shop_type": "convenience"
  },
  {
    "_id": "fba07347454b1e576a5cd4a5",
    "shop_id": "00013003",
    "shop_name": "CIRCLE K",
    "country_id": "VN",
    "province_id": "00",
    "district_id": "001",
    "ward_code": "00013",
    "house_number": "83",
    "street": "Phố Hàng Điếu",
    "latitude": 21.03206,
    "longitude": 105.84684,
    "shop_type": "convenience"
  },
  {
    "_id": "aea6ae6d514adeb95fc3b720",
    "shop_id": "00016001",
    "shop_name": "CIRCLE K",
    "country_id": "VN",
    "province_id": "00",
    "district_id": "001",
    "ward_code": "00016",
    "house_number": "85",
    "street": "Phố Hàng Mã",
    "latitude": 21.03656,
    "longitude": 105.84694,
    "shop_type": "convenience"
  },
  {
    "_id": "760630bca046f96158da5d8c",
    "shop_id": "00016002",
    "shop_name": "CIRCLE K",
    "country_id": "VN",
    "province_id": "00",
    "district_id": "001",
    "ward_code": "00016",
    "house_number": "79",
    "street": "Phố Hà Trung",
    "latitude": 21.03001,
    "longitude": 105.84486,
    "shop_type": "convenience"
  },
  {
    "_id": "9d80c3936aa80f90985f4bbe",
    "shop_id": "00016003",
    "shop_name": "CIRCLE K",
    "country_id": "VN",
    "province_id": "00",
    "district_id": "001",
    "ward_code": "00016",
    "house_number": "",
    "street": "Phố Hàng Than",
    "latitude": 21.04234,
    "longitude": 105.84714,
    "shop_type": "convenience"
  },
  {
    "_id": "0e5d54adf9e5251fb8e76f39",
    "shop_id": "00019001",
    "shop_name": "CIRCLE K",
    "country_id": "VN",
    "province_id": "00",
    "district_id": "001",
    "ward_code": "00019",
    "house_number": "79",
    "street": "Phố Hà Trung",
    "latitude": 21.03001,
    "longitude": 105.84486,
    "shop_type": "convenience"
  },
  {
    "_id": "64f9c2254fb0b07b82fa0ddf",
    "shop_id": "00019002",
    "shop_name": "CIRCLE K",
    "country_id": "VN",
    "province_id": "00",
    "district_id": "001",
    "ward_code": "00019",
    "house_number": "83",
    "street": "Phố Hàng Điếu",
    "latitude": 21.03206,
    "longitude": 105.84684,
    "shop_type": "convenience"
  },
  {
    "_id": "dda262d0b03ff367ea0425ac",
    "shop_id": "00019003",
    "shop_name": "CIRCLE K",
    "country_id": "VN",
    "province_id": "00",
    "district_id": "001",
    "ward_code": "00019",
    "house_number": "85",
    "street": "Phố Hàng Mã",
    "latitude": 21.03656,
    "longitude": 105.84694,
    "shop_type": "convenience"
  },
  {
    "_id": "321123154a42340d18bdcd9a",
    "shop_id": "00022001",
    "shop_name": "CIRCLE K",
    "country_id": "VN",
    "province_id": "00",
    "district_id": "001",
    "ward_code": "00022",
    "house_number": "79",
    "street": "Phố Hà Trung",
    "latitude": 21.03001,
    "longitude": 105.84486,
    "shop_type": "convenience"
  },
  {
    "_id": "84143a70933d4d7ee02dd601",
    "shop_id": "00022002",
    "shop_name": "CIRCLE K",
    "country_id": "VN",
    "province_id": "00",
    "district_id": "001",
    "ward_code": "00022",
    "house_number": "",
    "street": "Phố Hàng Bông",
    "latitude": 21.0293,
    "longitude": 105.84556,
    "shop_type": "convenience"
  },
  {
    "_id": "9a14c2dfe16b2a0b9d6fce37",
    "shop_id": "00022003",
    "shop_name": "CIRCLE K",
    "country_id": "VN",
    "province_id": "00",
    "district_id": "001",
    "ward_code": "00022",
    "house_number": "85",
    "street": "Phố Hàng Mã",
    "latitude": 21.03656,
    "longitude": 105.84694,
    "shop_type": "convenience"
  },
  {
    "_id": "e39c6f33d604328310d0a785",
    "shop_id": "00025001",
    "shop_name": "CIRCLE K",
    "country_id": "VN",
    "province_id": "00",
    "district_id": "001",
    "ward_code": "00025",
    "house_number": "79",
    "street": "Phố Hà Trung",
    "latitude": 21.03001,
    "longitude": 105.84486,
    "shop_type": "convenience"
  },
  {
    "_id": "e2f8835100c9a1522a9238f6",
    "shop_id": "00025002",
    "shop_name": "CIRCLE K",
    "country_id": "VN",
    "province_id": "00",
    "district_id": "001",
    "ward_code": "00025",
    "house_number": "",
    "street": "Phố Hàng Bông",
    "latitude": 21.0293,
    "longitude": 105.84556,
    "shop_type": "convenience"
  },
  {
    "_id": "2364f4a9e68121809bba0f87",
    "shop_id": "00025003",
    "shop_name": "CIRCLE K",
    "country_id": "VN",
    "province_id": "00",
    "district_id": "001",
    "ward_code": "00025",
    "house_number": "83",
    "street": "Phố Hàng Điếu",
    "latitude": 21.03206,
    "longitude": 105.84684,
    "shop_type": "convenience"
  },
  {
    "_id": "fe0d37d16d582e92dc1f8f0e",
    "shop_id": "00028001",
    "shop_name": "CIRCLE K",
    "country_id": "VN",
    "province_id": "00",
    "district_id": "001",
    "ward_code": "00028",
    "house_number": "79",
    "street": "Phố Hà Trung",
    "latitude": 21.03001,
    "longitude": 105.84486,
    "shop_type": "convenience"
  },
  {
    "_id": "f934139a0fb40fd1bfea53e7",
    "shop_id": "00028002",
    "shop_name": "CIRCLE K",
    "country_id": "VN",
    "province_id": "00",
    "district_id": "001",
    "ward_code": "00028",
    "house_number": "",
    "street": "Phố Hàng Bông",
    "latitude": 21.0293,
    "longitude": 105.84556,
    "shop_type": "convenience"
  },
  {
    "_id": "512080e58ae29582e2edab32",
    "shop_id": "00028003",
    "shop_name": "CIRCLE K",
    "country_id": "VN",
    "province_id": "00",
    "district_id": "001",
    "ward_code": "00028",
    "house_number": "83",
    "street": "Phố Hàng Điếu",
    "latitude": 21.03206,
    "longitude": 105.84684,
    "shop_type": "convenience"
  }
]